texoid/__init__.py
texoid/__main__.py
texoid/main.py
texoid/server.py
texoid/utils.py
texoid/backends/__init__.py
texoid/backends/direct.py
texoid/backends/docker.py
texoid-0.2.1.dist-info/LICENSE
texoid-0.2.1.dist-info/METADATA
texoid-0.2.1.dist-info/WHEEL
texoid-0.2.1.dist-info/entry_points.txt
texoid-0.2.1.dist-info/top_level.txt
texoid-0.2.1.dist-info/RECORD
