Metadata-Version: 2.1
Name: texoid
Version: 0.2.1
Summary: LaTeX math rendering server.
Home-page: https://github.com/DMOJ/texoid
Author: Quantum
Author-email: quantum@dmoj.ca
License: UNKNOWN
Platform: UNKNOWN
Classifier: Development Status :: 4 - Beta
Classifier: Environment :: Console
Classifier: Environment :: Web Environment
Classifier: Intended Audience :: Developers
Classifier: Intended Audience :: System Administrators
Classifier: License :: OSI Approved :: GNU Affero General Public License v3 or later (AGPLv3+)
Classifier: Operating System :: POSIX :: Linux
Classifier: Programming Language :: Python
Classifier: Programming Language :: Python :: 3 :: Only
Classifier: Topic :: Artistic Software
Classifier: Topic :: Multimedia :: Graphics :: Graphics Conversion
Classifier: Topic :: Software Development
Requires-Dist: tornado
Provides-Extra: test
Requires-Dist: requests ; extra == 'test'
